plone.exportimport-1.3.1-py3.12-nspkg.pth
plone/exportimport/__init__.py
plone/exportimport/configure.zcml
plone/exportimport/interfaces.py
plone/exportimport/settings.py
plone/exportimport/types.py
plone/exportimport/cli/__init__.py
plone/exportimport/deserializers/__init__.py
plone/exportimport/deserializers/blob.py
plone/exportimport/deserializers/blocks.py
plone/exportimport/deserializers/configure.zcml
plone/exportimport/exporters/__init__.py
plone/exportimport/exporters/base.py
plone/exportimport/exporters/configure.zcml
plone/exportimport/exporters/content.py
plone/exportimport/exporters/discussions.py
plone/exportimport/exporters/portlets.py
plone/exportimport/exporters/principals.py
plone/exportimport/exporters/redirects.py
plone/exportimport/exporters/relations.py
plone/exportimport/exporters/translations.py
plone/exportimport/importers/__init__.py
plone/exportimport/importers/base.py
plone/exportimport/importers/configure.zcml
plone/exportimport/importers/content.py
plone/exportimport/importers/discussions.py
plone/exportimport/importers/final.py
plone/exportimport/importers/portlets.py
plone/exportimport/importers/principals.py
plone/exportimport/importers/redirects.py
plone/exportimport/importers/relations.py
plone/exportimport/importers/translations.py
plone/exportimport/serializers/__init__.py
plone/exportimport/serializers/blob.py
plone/exportimport/serializers/blocks.py
plone/exportimport/serializers/configure.zcml
plone/exportimport/serializers/fields.py
plone/exportimport/testing/__init__.py
plone/exportimport/utils/__init__.py
plone/exportimport/utils/cli.py
plone/exportimport/utils/dates.py
plone/exportimport/utils/discussions.py
plone/exportimport/utils/path.py
plone/exportimport/utils/permissions.py
plone/exportimport/utils/portlets.py
plone/exportimport/utils/redirects.py
plone/exportimport/utils/relations.py
plone/exportimport/utils/translations.py
plone/exportimport/utils/zca.py
plone/exportimport/utils/content/__init__.py
plone_exportimport-1.3.1.dist-info/licenses/LICENSE
plone_exportimport-1.3.1.dist-info/METADATA
plone_exportimport-1.3.1.dist-info/WHEEL
plone_exportimport-1.3.1.dist-info/entry_points.txt
plone_exportimport-1.3.1.dist-info/namespace_packages.txt
plone_exportimport-1.3.1.dist-info/top_level.txt
plone_exportimport-1.3.1.dist-info/RECORD
