Metadata-Version: 2.4
Name: plone.exportimport
Version: 1.3.1
Summary: Plone content export / import support
Home-page: https://plone.org
Author: Plone Foundation
Author-email: releasemanager@plone.org
License: GPL version 2
Project-URL: Homepage, https://plone.org
Project-URL: Documentation, https://6.docs.plone.org
Project-URL: Source, https://github.com/plone/plone.exportimport
Project-URL: Issues, https://github.com/plone/plone.exportimport/issues
Keywords: Plone CMF Python Zope CMS
Classifier: Development Status :: 5 - Production/Stable
Classifier: Environment :: Web Environment
Classifier: Framework :: Plone
Classifier: Framework :: Plone :: 6.0
Classifier: Framework :: Plone :: 6.1
Classifier: Framework :: Plone :: 6.2
Classifier: Framework :: Plone :: Core
Classifier: Framework :: Zope :: 5
Classifier: License :: OSI Approved :: GNU General Public License v2 (GPLv2)
Classifier: Operating System :: OS Independent
Classifier: Programming Language :: Python
Classifier: Programming Language :: Python :: 3.8
Classifier: Programming Language :: Python :: 3.9
Classifier: Programming Language :: Python :: 3.10
Classifier: Programming Language :: Python :: 3.11
Classifier: Programming Language :: Python :: 3.12
Classifier: Programming Language :: Python :: 3.13
Requires-Python: >=3.8
License-File: LICENSE
Requires-Dist: python-dateutil
Requires-Dist: plone.api
Requires-Dist: plone.app.contenttypes
Requires-Dist: plone.app.dexterity
Requires-Dist: plone.app.redirector
Requires-Dist: plone.app.textfield
Requires-Dist: plone.app.users
Requires-Dist: plone.base
Requires-Dist: plone.dexterity
Requires-Dist: plone.namedfile
Requires-Dist: plone.restapi
Requires-Dist: plone.uuid
Requires-Dist: Products.CMFEditions
Requires-Dist: Products.CMFPlone
Requires-Dist: Products.DCWorkflow
Requires-Dist: Products.PlonePAS
Requires-Dist: Products.PortalTransforms
Requires-Dist: setuptools
Requires-Dist: z3c.relationfield
Requires-Dist: zc.relation
Requires-Dist: Zope
Provides-Extra: test
Requires-Dist: zest.releaser[recommended]; extra == "test"
Requires-Dist: zestreleaser.towncrier; extra == "test"
Requires-Dist: plone.app.discussion; extra == "test"
Requires-Dist: plone.app.iterate; extra == "test"
Requires-Dist: plone.app.multilingual; extra == "test"
Requires-Dist: plone.app.testing; extra == "test"
Requires-Dist: plone.app.upgrade; extra == "test"
Requires-Dist: plone.restapi[test]; extra == "test"
Requires-Dist: plone.volto[test]; extra == "test"
Requires-Dist: plone.testing; extra == "test"
Requires-Dist: pytest; extra == "test"
Requires-Dist: pytest-cov; extra == "test"
Requires-Dist: pytest-plone>=0.5.0; extra == "test"
Dynamic: author
Dynamic: author-email
Dynamic: classifier
Dynamic: description
Dynamic: description-content-type
Dynamic: home-page
Dynamic: keywords
Dynamic: license
Dynamic: license-file
Dynamic: project-url
Dynamic: provides-extra
Dynamic: requires-dist
Dynamic: requires-python
Dynamic: summary
